dgp_server/VERSION
dgp_server/__init__.py
dgp_server/blueprint.py
dgp_server/config_storer.py
dgp_server/configurations.py
dgp_server/line_selector.py
dgp_server/log.py
dgp_server/poster.py
dgp_server/publish_flow.py
dgp_server/row_sender.py
dgp_server/server.py
dgp_server-0.0.95.dist-info/LICENSE
dgp_server-0.0.95.dist-info/METADATA
dgp_server-0.0.95.dist-info/WHEEL
dgp_server-0.0.95.dist-info/top_level.txt
dgp_server-0.0.95.dist-info/RECORD
