Metadata-Version: 2.1
Name: dgp-server
Version: 0.0.95
Summary: A server for running dgp
Home-page: https://github.com/dataspot/dgp-server
Author: Adam Kariv
Author-email: adam.kariv@gmail.com
License: MIT
Keywords: data
Platform: UNKNOWN
Classifier: Development Status :: 4 - Beta
Classifier: Intended Audience :: Developers
Classifier: License :: OSI Approved :: MIT License
Classifier: Operating System :: OS Independent
Classifier: Programming Language :: Python :: 3.6
Classifier: Programming Language :: Python :: 3.7
Classifier: Topic :: Software Development :: Libraries :: Python Modules
Requires-Dist: dgp (>=0.0.98)
Requires-Dist: gunicorn
Requires-Dist: aiohttp
Requires-Dist: aiohttp-sse
Requires-Dist: psycopg2-binary
Provides-Extra: develop
Requires-Dist: pylama ; extra == 'develop'
Requires-Dist: tox ; extra == 'develop'
